ssdas/__init__.py
ssdas-0.0.1.dist-info/METADATA
ssdas-0.0.1.dist-info/WHEEL
ssdas-0.0.1.dist-info/top_level.txt
ssdas-0.0.1.dist-info/RECORD
